CHANGES.txt
README.txt
bootstrap.py
buildout.cfg
setup.cfg
setup.py
docs/HISTORY.txt
docs/README.txt
docs/index.html
docs/sample.ini
docs/images/index.html
docs/images/python.jpg
iw/__init__.py
iw.thumbs.egg-info/PKG-INFO
iw.thumbs.egg-info/SOURCES.txt
iw.thumbs.egg-info/dependency_links.txt
iw.thumbs.egg-info/entry_points.txt
iw.thumbs.egg-info/namespace_packages.txt
iw.thumbs.egg-info/not-zip-safe
iw.thumbs.egg-info/requires.txt
iw.thumbs.egg-info/top_level.txt
iw/thumbs/README.txt
iw/thumbs/__init__.py
iw/thumbs/application.py
iw/thumbs/image.py
iw/thumbs/middleware.py
iw/thumbs/url.py
iw/thumbs/url.txt
iw/thumbs/tests/__init__.py
iw/thumbs/tests/logo.png
iw/thumbs/tests/test_docs.py